README.md
setup.py
core/__init__.py
core/client.py
core/compat.py
core/request.py
core/auth/__init__.py
core/auth/credentials.py
core/auth/algorithm/__init__.py
core/auth/algorithm/sha_hmac1.py
core/auth/algorithm/sha_hmac256.py
core/auth/composer/__init__.py
core/auth/composer/roa_signature_composer.py
core/auth/composer/rpc_signature_composer.py
core/auth/signers/__init__.py
core/auth/signers/access_key_signer.py
core/auth/signers/rsa_key_pair_signer.py
core/auth/signers/signer.py
core/auth/signers/signer_factory.py
core/auth/utils/__init__.py
core/data/endpoints.json
core/data/retry_config.json
core/data/timeout_config.json
core/endpoint/__init__.py
core/endpoint/chained_endpoint_resolver.py
core/endpoint/default_endpoint_resolver.py
core/endpoint/endpoint_resolver_base.py
core/endpoint/local_config_global_endpoint_resolver.py
core/endpoint/local_config_regional_endpoint_resolver.py
core/endpoint/location_service_endpoint_resolver.py
core/endpoint/resolver_endpoint_request.py
core/endpoint/user_customized_endpoint_resolver.py
core/endpoint/location/DescribeEndpointsRequest.py
core/endpoint/location/__init__.py
core/exception/__init__.py
core/exception/error_code.py
core/exception/error_msg.py
core/exception/error_type.py
core/exception/exceptions.py
core/http/__init__.py
core/http/format_type.py
core/http/http_request.py
core/http/http_response.py
core/http/method_type.py
core/http/protocol_type.py
core/profile/__init__.py
core/profile/region_provider.py
core/retry/__init__.py
core/retry/backoff_strategy.py
core/retry/retry_condition.py
core/retry/retry_policy.py
core/retry/retry_policy_context.py
core/utils/__init__.py
core/utils/parameter_helper.py
core/utils/validation.py
core/vendored/__init__.py
core/vendored/six.py
core/vendored/requests/__init__.py
core/vendored/requests/__version__.py
core/vendored/requests/_internal_utils.py
core/vendored/requests/adapters.py
core/vendored/requests/api.py
core/vendored/requests/auth.py
core/vendored/requests/certs.py
ipaas_python_sdk_core.egg-info/PKG-INFO
ipaas_python_sdk_core.egg-info/SOURCES.txt
ipaas_python_sdk_core.egg-info/dependency_links.txt
ipaas_python_sdk_core.egg-info/requires.txt
ipaas_python_sdk_core.egg-info/top_level.txt
