Metadata-Version: 1.1
Name: ipaas-python-sdk-core
Version: 1.0.0
Summary: The ipaas-openapi Python SDK.
Home-page: UNKNOWN
Author: ClickPaas Cloud
Author-email: UNKNOWN
License: Apache License 2.0
Keywords: ipaas,sdk,core
Platform: any
Classifier: Development Status :: 5 - Production/Stable
Classifier: Intended Audience :: Developers
Classifier: License :: OSI Approved :: Apache Software License
Classifier: Programming Language :: Python
Classifier: Programming Language :: Python :: 2.6
Classifier: Programming Language :: Python :: 2.7
Classifier: Programming Language :: Python :: 3
Classifier: Programming Language :: Python :: 3.3
Classifier: Programming Language :: Python :: 3.4
Classifier: Programming Language :: Python :: 3.5
Classifier: Programming Language :: Python :: 3.6
Classifier: Programming Language :: Python :: 3.7
Classifier: Topic :: Software Development
